documented/__init__.py
documented/contrib/__init__.py
documented/contrib/rich_markdown.py
documented/documented.py
documented/error.py
documented/untouchable.py
documented-0.1.4.dist-info/LICENSE
documented-0.1.4.dist-info/METADATA
documented-0.1.4.dist-info/WHEEL
documented-0.1.4.dist-info/RECORD
